pySerialTransfer/__init__.py
pySerialTransfer/pySerialTransfer.py
pySerialTransfer-1.0.2.dist-info/METADATA
pySerialTransfer-1.0.2.dist-info/WHEEL
pySerialTransfer-1.0.2.dist-info/top_level.txt
pySerialTransfer-1.0.2.dist-info/RECORD
